autograder/__init__.py
autograder/io_utils.py
autograder/printing.py
autograder/testsuite.py
autograder/tests/ArgTest.py
autograder/tests/BaseTest.py
autograder/tests/FileIOTest.py
autograder/tests/IOTest.py
autograder/tests/TestResponse.py
autograder/tests/__init__.py
autograder/tests/errors.py
sp_autograder-0.2.dist-info/LICENSE.txt
sp_autograder-0.2.dist-info/METADATA
sp_autograder-0.2.dist-info/WHEEL
sp_autograder-0.2.dist-info/top_level.txt
sp_autograder-0.2.dist-info/RECORD
