Metadata-Version: 2.1
Name: sp-autograder
Version: 0.2
Summary: A Python-backed customizable autograder.
Home-page: https://github.com/stanfordpython/autograder
Author: Parth Sarin
Author-email: psarin@stanford.edu
License: MIT
Keywords: EDUCATION,TESTING,AUTOGRADER
Platform: UNKNOWN
Classifier: Environment :: Console
Classifier: Intended Audience :: Developers
Classifier: Intended Audience :: Education
Classifier: Topic :: Education
Classifier: License :: OSI Approved :: MIT License
Classifier: Programming Language :: Python :: 3
Classifier: Programming Language :: Python :: 3.8
Requires-Dist: pycodestyle (>=2.5.0)
